setup.py
tuvedi/__init__.py
tuvedi.egg-info/PKG-INFO
tuvedi.egg-info/SOURCES.txt
tuvedi.egg-info/dependency_links.txt
tuvedi.egg-info/entry_points.txt
tuvedi.egg-info/requires.txt
tuvedi.egg-info/top_level.txt
tuvedi/admin/__init__.py
tuvedi/admin/component.py
tuvedi/admin/device.py
tuvedi/admin/filter.py
tuvedi/admin/layout.py
tuvedi/admin/presentation.py
tuvedi/admin/template.py
tuvedi/admin/widget.py
tuvedi/tool/__init__.py
tuvedi/web/__init__.py