Metadata-Version: 1.0
Name: tuvedi
Version: 0.3
Summary: TuVedi is a tool to manage content on info displays
Home-page: UNKNOWN
Author: TuVedi Team
Author-email: UNKNOWN
License: UNKNOWN
Platform: UNKNOWN
Classifier: Development Status :: 3 - Alpha
Classifier: License :: OSI Approved :: GNU General Public License (GPL)
Classifier: Programming Language :: Python
Classifier: Topic :: Internet :: WWW/HTTP :: Dynamic Content
